Kookbook.py
MANIFEST.in
MIT-LICENSE
README.txt
setup.py
lib/cmdopt.py
lib/Cmdopt.egg-info/PKG-INFO
lib/Cmdopt.egg-info/SOURCES.txt
lib/Cmdopt.egg-info/dependency_links.txt
lib/Cmdopt.egg-info/requires.txt
lib/Cmdopt.egg-info/top_level.txt
test/cmdopt_test.py